README.md
pyproject.toml
setup.py
test/test_fragment.py
test/test_morgan.py
test/test_netx.py
test/test_remap.py
test/test_tanimoto.py
xenosite/fragment/__init__.py
xenosite/fragment/__main__.py
xenosite/fragment/_static_version.py
xenosite/fragment/_version.py
xenosite/fragment/chem.py
xenosite/fragment/feature.py
xenosite/fragment/graph.py
xenosite/fragment/keras_backend.py
xenosite/fragment/netx.py
xenosite/fragment/ops.py
xenosite/fragment/remap.py
xenosite/fragment/serialize.py
xenosite/fragment/stats.py
xenosite_fragment.egg-info/PKG-INFO
xenosite_fragment.egg-info/SOURCES.txt
xenosite_fragment.egg-info/dependency_links.txt
xenosite_fragment.egg-info/entry_points.txt
xenosite_fragment.egg-info/requires.txt
xenosite_fragment.egg-info/top_level.txt