Metadata-Version: 2.1
Name: xenosite-fragment
Version: 0a11
Summary: Library for molecule fragment operations.
Home-page: UNKNOWN
Author: S. Joshua Swamidass
Author-email: swamidass@wustl.edu
License: UNKNOWN
Platform: UNKNOWN
Classifier: Intended Audience :: Education
Classifier: Intended Audience :: Science/Research
Classifier: Natural Language :: English
Classifier: Operating System :: MacOS
Classifier: Operating System :: POSIX :: Linux
Classifier: Programming Language :: Python
Classifier: Programming Language :: Python :: 3.9
Classifier: Programming Language :: Python :: 3.10
Classifier: Topic :: Scientific/Engineering :: Chemistry
Classifier: Typing :: Typed
